littletable.py
littletable-3.0.2.dist-info/licenses/LICENSE
littletable-3.0.2.dist-info/METADATA
littletable-3.0.2.dist-info/WHEEL
littletable-3.0.2.dist-info/top_level.txt
littletable-3.0.2.dist-info/RECORD
