Metadata-Version: 2.4
Name: littletable
Version: 3.0.2
Summary: Python in-memory ORM database
Author-email: Paul McGuire <ptmcg@austin.rr.com>
Maintainer-email: Paul McGuire <ptmcg@austin.rr.com>
License-Expression: MIT
Project-URL: Homepage, https://github.com/ptmcg/littletable/
Project-URL: Download, https://pypi.org/project/littletable/
Classifier: Development Status :: 5 - Production/Stable
Classifier: Intended Audience :: Developers
Classifier: Intended Audience :: Information Technology
Classifier: Intended Audience :: Science/Research
Classifier: Operating System :: OS Independent
Classifier: Programming Language :: Python
Classifier: Programming Language :: Python :: 3
Classifier: Programming Language :: Python :: 3 :: Only
Classifier: Programming Language :: Python :: 3.9
Classifier: Programming Language :: Python :: 3.10
Classifier: Programming Language :: Python :: 3.11
Classifier: Programming Language :: Python :: 3.12
Classifier: Programming Language :: Python :: 3.13
Classifier: Programming Language :: Python :: 3.14
Classifier: Topic :: Database
Requires-Python: >=3.9
License-File: LICENSE
Dynamic: license-file
